plbm_liuyi778_Stable/AptManage.py
plbm_liuyi778_Stable/Cmd.py
plbm_liuyi778_Stable/Docker.py
plbm_liuyi778_Stable/Dpkg.py
plbm_liuyi778_Stable/FileManagement.py
plbm_liuyi778_Stable/Iptables.py
plbm_liuyi778_Stable/Jurisdiction.py
plbm_liuyi778_Stable/NetManagement.py
plbm_liuyi778_Stable/NetStatus.py
plbm_liuyi778_Stable/OsInfo.py
plbm_liuyi778_Stable/Package.py
plbm_liuyi778_Stable/README.md
plbm_liuyi778_Stable/Service.py
plbm_liuyi778_Stable/Source.py
plbm_liuyi778_Stable/Yum.py
plbm_liuyi778_Stable/__init__.py
plbm_liuyi778_Stable/base.py
plbm_liuyi778_Stable/get.py
plbm_liuyi778_Stable/logger.py
plbm_liuyi778_Stable/requirements.txt
plbm_liuyi778_Stable/txt.log
plbm_liuyi778_Stable/security/__init__.py
plbm_liuyi778_Stable/security/firewalld.py
plbm_liuyi778_stable-1.3.6.dist-info/METADATA
plbm_liuyi778_stable-1.3.6.dist-info/WHEEL
plbm_liuyi778_stable-1.3.6.dist-info/licenses/LICENSE
plbm_liuyi778_stable-1.3.6.dist-info/RECORD
